pipautocompile/__init__.py
pipautocompile/docker.py
pipautocompile/git.py
pipautocompile/io.py
pipautocompile/logging.py
pipautocompile/main.py
pipautocompile/py.typed
pipautocompile/utils.py
pip_autocompile-0.7.16.dist-info/LICENSE
pip_autocompile-0.7.16.dist-info/METADATA
pip_autocompile-0.7.16.dist-info/WHEEL
pip_autocompile-0.7.16.dist-info/entry_points.txt
pip_autocompile-0.7.16.dist-info/RECORD
