Metadata-Version: 2.1
Name: pip-autocompile
Version: 0.7.16
Summary: Automate pip-compile for multiple environments.
Home-page: https://github.com/KSmanis/pip-autocompile
License: MIT
Author: Konstantinos Smanis
Author-email: konstantinos.smanis@gmail.com
Requires-Python: >=3.9,<4.0
Classifier: Development Status :: 3 - Alpha
Classifier: Environment :: Console
Classifier: Intended Audience :: Developers
Classifier: License :: OSI Approved :: MIT License
Classifier: Operating System :: OS Independent
Classifier: Programming Language :: Python :: 3
Classifier: Programming Language :: Python :: 3.9
Classifier: Programming Language :: Python :: 3.10
Classifier: Programming Language :: Python :: 3.11
Classifier: Programming Language :: Python :: 3.12
Classifier: Programming Language :: Python :: 3.13
Classifier: Topic :: Software Development :: Build Tools
Requires-Dist: click (>=8.1.7,<9.0.0)
Requires-Dist: dockerfile (>=3.3.1,<4.0.0)
Requires-Dist: pygit2 (>=1.15.1,<1.16.0) ; python_version >= "3.9" and python_version < "3.10"
Requires-Dist: pygit2 (>=1.16.0,<2.0.0) ; python_version >= "3.10" and python_version < "4.0"
Requires-Dist: python-on-whales (>=0.73.0,<0.74.0)
Project-URL: Repository, https://github.com/KSmanis/pip-autocompile
